[
  {
    "name": " Southern Spice",
    "type": "Restaurant",
    "pos": {
      "lat": 29.787286,
      "lng": -95.7948816
    }
  },
  {
    "name": "Kirpal Dhaba",
    "type": "Dhabha",
    "pos": {
      "lat": 29.787286,
      "lng": -95.7948816
    }
  },
  {
    "name": " The Food Lounge",
    "type": "Coffee Shop",
    "pos": {
      "lat": 29.787286,
      "lng": -95.7948816
    }
  },
  {
    "name": "Silver Spoon",
    "type": "Multi Cuisine",
    "pos": {
      "lat": 29.787286,
      "lng": -95.7948816
    }
  },
  {
    "name": "Dominos Pizza",
    "type": "Pizza",
    "pos": {
      "lat": 29.787286,
      "lng": -95.7948816
    }
  }
]
